fs/rclonefs/__init__.py
fs/rclonefs/_version.txt
fs/rclonefs/file.py
fs/rclonefs/rclone.py
fs/rclonefs/rclonefs.py
fs_rclonefs-0.5.1.dist-info/METADATA
fs_rclonefs-0.5.1.dist-info/WHEEL
fs_rclonefs-0.5.1.dist-info/licenses/LICENSE
fs_rclonefs-0.5.1.dist-info/RECORD
