Metadata-Version: 2.3
Name: fs.rclonefs
Version: 0.5.1
Summary: Pyfilesystem interface to control rclone remotes.
Project-URL: Homepage, https://github.com/element0/fs.rclonefs
Project-URL: Issues, https://github.com/element0/fs.rclonefs/issues
Author-email: Raygan Henley <raygan@raygan.com>
License-File: LICENSE
Classifier: License :: OSI Approved :: MIT License
Classifier: Operating System :: OS Independent
Classifier: Programming Language :: Python :: 3
Requires-Python: >=3.9
Requires-Dist: fs~=2.4.12
